pymato.py
pymato-0.1.8.dist-info/DESCRIPTION.rst
pymato-0.1.8.dist-info/METADATA
pymato-0.1.8.dist-info/RECORD
pymato-0.1.8.dist-info/WHEEL
pymato-0.1.8.dist-info/entry_points.txt
pymato-0.1.8.dist-info/metadata.json
pymato-0.1.8.dist-info/top_level.txt
