Metadata-Version: 2.0
Name: pymato
Version: 0.1.8
Summary: Simple command line pomodoro timer
Home-page: https://github.com/waynew/pymato
Author: Wayne Werner
Author-email: waynejwerner@gmail.com
License: MIT
Keywords: console,countdown,stopwatch,terminal,timer,pomodoro
Platform: UNKNOWN
Classifier: Development Status :: 3 - Alpha
Classifier: Environment :: Console :: Curses
Classifier: License :: OSI Approved :: MIT License
Classifier: Natural Language :: English
Classifier: Operating System :: MacOS :: MacOS X
Classifier: Operating System :: POSIX
Classifier: Operating System :: Unix
Classifier: Programming Language :: Python :: 3.5
Classifier: Programming Language :: Python :: 3.6
Classifier: Programming Language :: Python :: 3.7
Classifier: Topic :: Utilities
Requires-Dist: pytz
Requires-Dist: tzlocal
